{   "NNODES": 70,
    "NREPS": 100,
    "DATE_STRING": "091720",
    "SAVEDATA" : 1,
    "NAMETAG_creategraphs": "graphs",
    "HOMEDIR": "/cbica/home/sizemora/git_repos/Noise_and_TDA",
    "save_dir_graphs": "processed_data/graphs",
    "save_dir_thresh": "processed_data/thresholded_graphs",
    "read_dir_thresh": "processed_data/thresholded_graphs",
    "MAXDIM": 4,
    "SAVETAIL_ph_forward": "eireneoutput_forward",
    "read_dir_graphs": "processed_data/graphs",
    "save_dir_results": "processed_data/results",
    "SAVETAIL_ph_backward": "eireneoutput_backward",
    "SAVETAIL_ph_thresholds": "eireneoutput_threshold",
    "NAMEID_ph_thresholds": "thresh",
    "THRESHVEC": [0.2, 0.3, 0.4, 0.5, 0.6, 0.7, 0.8],
    "SAVETAIL_threshold_graphs": "rho",
    "SAVETAIL_ph_noiseOnly": "eireneoutput_noiseOnly",
    "save_dir_forJason": "processed_data/forJason",
    "read_dir_results": "processed_data/results",
    "SAVETAIL_bettiBars": "bettiBars",
    "SAVETAIL_bettis": "bettis",
    "SAVETAIL_graphInfo": "graphInfo",
    "SAVETAIL_netStats": "netStats",
    "SAVETAIL_ph_conecheck": "conelevel",
    "graph_models": 
        {
            "probTriangle99": {"fn": "make_probtriangle", "parameters": [0.99], "name": "probTriangle99", "flag": "create"},
            "probTriangle98": {"fn": "make_probtriangle", "parameters": [0.98], "name": "probTriangle98", "flag": "create"},
            "probTriangle97": {"fn": "make_probtriangle", "parameters": [0.97], "name": "probTriangle97", "flag": "create"},
            "probTriangle96": {"fn": "make_probtriangle", "parameters": [0.96], "name": "probTriangle96", "flag": "create"},
            "probTriangle95": {"fn": "make_probtriangle", "parameters": [0.95], "name": "probTriangle95", "flag": "create"},
            "probTriangle94": {"fn": "make_probtriangle", "parameters": [0.94], "name": "probTriangle94", "flag": "create"},
            "probTriangle93": {"fn": "make_probtriangle", "parameters": [0.93], "name": "probTriangle93", "flag": "create"},
            "probTriangle92": {"fn": "make_probtriangle", "parameters": [0.92], "name": "probTriangle92", "flag": "create"},
            "probTriangle91": {"fn": "make_probtriangle", "parameters": [0.91], "name": "probTriangle91", "flag": "create"}
        }
    }
